urequest/__init__.py
urequest/credentials.py
urequest/response.py
urequest/session.py
urequest/url.py
urequest-0.0.6.dist-info/AUTHORS.md
urequest-0.0.6.dist-info/LICENSE.md
urequest-0.0.6.dist-info/METADATA
urequest-0.0.6.dist-info/WHEEL
urequest-0.0.6.dist-info/top_level.txt
urequest-0.0.6.dist-info/RECORD
