Metadata-Version: 2.1
Name: urequest
Version: 0.0.6
Summary: Provides user-friendly HTTP client with clean objects.
Home-page: https://github.com/vyahello/urequest
Author: Volodymyr Yahello
Author-email: vyahello@gmail.com
License: UNKNOWN
Platform: UNKNOWN
Classifier: Programming Language :: Python :: 3.6
Classifier: Programming Language :: Python :: 3.7
Classifier: Programming Language :: Python :: 3.8
Classifier: License :: OSI Approved :: MIT License
Classifier: Operating System :: OS Independent
Requires-Python: >=3.6
Requires-Dist: requests (==2.23.0)
Requires-Dist: dataclasses (==0.6.0)
Requires-Dist: enforce-pep8 (==0.0.7)
